hypermodern_python_cli99/__init__.py
hypermodern_python_cli99/console.py
hypermodern_python_cli99/wikipedia.py
hypermodern_python_cli99-0.2.0.dist-info/entry_points.txt
hypermodern_python_cli99-0.2.0.dist-info/LICENSE
hypermodern_python_cli99-0.2.0.dist-info/WHEEL
hypermodern_python_cli99-0.2.0.dist-info/METADATA
hypermodern_python_cli99-0.2.0.dist-info/RECORD
